py1dtdf/__init__.py
py1dtdf/features.py
py1dtdf-1.0.1.dist-info/LICENSE
py1dtdf-1.0.1.dist-info/METADATA
py1dtdf-1.0.1.dist-info/WHEEL
py1dtdf-1.0.1.dist-info/top_level.txt
py1dtdf-1.0.1.dist-info/RECORD
